zepben/eas/__init__.py
zepben/eas/client/__init__.py
zepben/eas/client/eas_client.py
zepben/eas/client/feeder_load_analysis_input.py
zepben/eas/client/fla_forecast_config.py
zepben/eas/client/hc_commons.py
zepben/eas/client/ingestor.py
zepben/eas/client/opendss.py
zepben/eas/client/study.py
zepben/eas/client/util.py
zepben/eas/client/work_package.py
zepben_eas-0.27.0.dist-info/licenses/LICENSE
zepben_eas-0.27.0.dist-info/METADATA
zepben_eas-0.27.0.dist-info/WHEEL
zepben_eas-0.27.0.dist-info/top_level.txt
zepben_eas-0.27.0.dist-info/RECORD
