Metadata-Version: 2.4
Name: zepben.eas
Version: 0.27.0
Summary: Python SDK for interacting with the Evolve App Server
Author-email: Ramon Bouckaert <ramon.bouckaert@zepben.com>, Max Chesterfield <max.chesterfield@zepben.com>
License-Expression: MPL-2.0
Project-URL: Repository, https://github.com/zepben/eas-python-client
Project-URL: Homepage, https://zepben.com
Classifier: Programming Language :: Python :: 3
Classifier: Programming Language :: Python :: 3.10
Classifier: Programming Language :: Python :: 3.11
Classifier: Programming Language :: Python :: 3.12
Classifier: Programming Language :: Python :: 3.13
Classifier: Operating System :: OS Independent
Requires-Python: >=3.10
License-File: LICENSE
Requires-Dist: geojson==2.5.0
Requires-Dist: requests<3.0.0,>=2.26.0
Requires-Dist: urllib3==2.5.0
Requires-Dist: zepben.ewb==1.1.0
Requires-Dist: aiohttp[speedups]==3.9.0
Provides-Extra: test
Requires-Dist: pytest; extra == "test"
Requires-Dist: pytest-cov; extra == "test"
Requires-Dist: pytest-httpserver==1.0.8; extra == "test"
Requires-Dist: trustme==0.9.0; extra == "test"
Dynamic: license-file
